{
	"name": "ds_data_output",
	"properties": {
		"linkedServiceName": {
			"referenceName": "ls_data_output",
			"type": "LinkedServiceReference"
		},
		"annotations": [],
		"type": "DelimitedText",
		"typeProperties": {
			"location": {
				"type": "AzureBlobStorageLocation",
				"folderPath": "output1",
				"container": "testcontainerabhishekh"
			},
			"columnDelimiter": ",",
			"escapeChar": "\\",
			"firstRowAsHeader": true,
			"quoteChar": "\""
		},
		"schema": [
			{
				"name": "id",
				"type": "String"
			},
			{
				"name": "name",
				"type": "String"
			},
			{
				"name": "gender",
				"type": "String"
			},
			{
				"name": "salary",
				"type": "String"
			}
		]
	}
}